{"title":"数学的準備","markdown":{"headingText":"数学的準備","containsRefs":false,"markdown":"\n## 前説\n\nこの章では物理の世界に入る前に知っておかなければならないことを説明します．\n$\\require{physics}$\n\n物理学を始める際にして、初学者の方にはどうしてもある程度の数学の素養が求められます。物理学の発展と数学は決して離すことのできない物であり、例えばみなさんがこれかあら学ぶ力学の分野は、微分と積分の関係性を発見し、それを基礎にしてニュートンが発展させた分野です。\n\nですがそこが最大の関門として高校生の皆様には立ちはだかることになると思います．ベクトルも微分も積分も，なんなら三角関数もまともにやったことがないのに，いきなり全部を使いこなせることを要求されてしまうからです．\n\nなので，この章では読者が高校2年生の途中くらいから読み始めているものだと想定して，数学について少しずつ勉強を進めながら，物理を始められるところまでやっていこうと思います．関数の定義や三角関数については流石にもう慣れてきたのではないかという時期ですね．もしもまだそこがあやふやであるのならば，まずは数学の教科書をある程度進ませてからこの本を読んでいただければ幸いと思っています．\n\nまた，初学者の方でもある程度は学びを進められるように配慮はしてありますが，もしもこの本の記述が難しい，ついていけないように感じられるのであれば，高等学校の教科書や市販の参考書などとともに読み進めていただくと良いかもしれません．\n\nですが，すでに一通り数学をやっている方ならば，この章を飛ばしていただいても構いません．そのための指標として，まずはこの章におけるゴールを一通り書いておきます．次の表に載せてあることを理解できるようになれば，ひとまずこの章は学び終えたという判定で考えてもらって構いません．\n\n::: {.callout-note icon=false}\n\n## 数学の公式\n\n|||\n|-|---|\n|微分の定義| $$\\dv{x} f(x)=\\lim_{\\Delta x\\rightarrow 0}\\frac{f(x+\\Delta x)-f(x)}{\\Delta x}$$ |\n|積の微分法| $$\\dv{x}\\{f(x)g(x)\\}=f'(x)g(x)+f(x)g'(x)$$ |\n|商の微分法| $$\\dv{x}\\{\\frac{f(x)}{g(x)}\\}=\\frac{f'(x)g(x)-f(x)g'(x)}{\\{g(x)\\}^2}$$|\n|冪函数の微分法| $$\\dv{x}x^r=rx^{r-1}$$ |\n\n: {tbl-colwidths=\"[25,75]\"}\n\n:::\n\nでは，始めましょう．\n\n## 極限\n\n関数 $f(x)=\\frac{1}{x}$ を考えます．分母の値である $x$ が $1,10,100,...$ と大きくなるにつれて，関数の値は $1,0.1,0.01,...$ と小さくなっていきますね．このような状態のことを次のように書く記すことにします．\n\n$$x \\to \\infty \\; \\text{のとき，} \\frac{1}{x} \\to 0$$\n\nまたは，\n\n$$ \\lim_{x\\to\\infty}\\frac{1}{x}=0$$\n\nこの本では後者の方にまとめて書くことにします．\n\nまた同様にして，分母の値である $x$ が $-1,-10,-100,...$ と大きくなるにつれて，関数の値は $-1,-0.1,-0.01,...$ と $0$ に近づくことが確認されます．このような状態も次のように書く記すことにします．\n\n$$ \\lim_{x\\to-\\infty}\\frac{1}{x}=0$$\n\n次に，分母の値である $x$ が $1,0.1,0.01,...$ と正の値を保ちつつ小さくなる( $0$ に近づく)につれて，関数の値は $1,10,100,...$ と限りなく大きくなることが確認できます．このような状態も次のように書く記すことにします．\n\n$$ \\lim_{x\\to +0}\\frac{1}{x}=\\infty$$\n\n最後に分母の値である $x$ が $-1,-0.1,-0.01,...$ と負の値を保ちつつ小さくなるにつれて，関数の値は $-1,-10,-100,...$ と限りなく小さくなることが確認できます．このような状態も次のように書く記すことにします．\n\n$$ \\lim_{x\\to -0}\\frac{1}{x}=-\\infty$$\n\n以上の話をまとめると次のようになります．\n\n::: {.callout-note icon=false}\n\n## 定理\n\n分数の分子が $0$ でない定数の時，分母の絶対値が大きくなると分数の値は $0$ に限りなく近づき，分母が $0$ に近づくと分数の絶対値は限りなく大きくなる．\n:::\n\nこの定理の前半を証明するには $\\frac{c}{x}$ についてどんなに小さな正の数 $h$ が指定されようとも， $|\\frac{c}{x}|<h$ となる $x$ が存在することを示せば良いです．例えば $|x|>\\frac{|c|}{h}+1$ などが存在します．後半については，$\\frac{c}{x}$ についてどんなに大きな正の数 $G$ が指定されようとも， $|\\frac{c}{x}| > G$ となる $x$ が存在することを示せば良いです．例えば $0<|x|<\\frac{|c|}{G}$ を満たす $x$ などが存在します．\n\n## 収束\n\n次に，大事な事項である収束について説明します．\n\nまず，次のような関数を考えましょう．\n\n$$f(x) = \\frac{x^2-1}{x-1}$$\n\nこの関数は $x=1$ では定義されません．なぜなら，分母が $0$ になってしまうからです．では，この関数の $x=1$ 周辺での様子はどうなっているのでしょうか．周辺なので， $x\\neq 1$ とすることができます．なので，その時に限り，\n\n$$f(x) = \\frac{x^2-1}{x-1}=\\frac{(x+1)(x-1)}{x-1}=x+1$$\n\nと式変形することができ， $x+1$ の値は $x$ が限りなく $1$ に近づく際には， $2$ に限りなく近づくことになります．この状態のことを次のように書き表します．\n\n$$ \\lim_{x\\to 1}f(x)=2$$\n\nこのことをまとめ上げると次のようになります．\n\n::: {.callout-note icon=false}\n\n## 定義\n\n$f(x)$ が $x=a$ の近くで定義されている関数で， $x$ が $a$ に近づく時，$f(x)$ が限りなく $\\alpha$ に近づく時，次のように書く．\n\n$$ \\lim_{x\\to a}f(x)=\\alpha$$\n\nただし， $f(x)$ は $x=a$ において定義されていなくとも良い．また， $x$ が $a$ より大きな値から $a$ に近づくときは $\\lim_{x\\to a+0}$ と書き，$x$ が $a$ より小さな値から $a$ に近づくときは $\\lim_{x\\to a-0}$ と書く．\n\n:::\n\n以上の知識を持って，実際に問題を解いてみましょう．\n\n::: {.callout-tip icon=false}\n\n## 問題\n\n|||\n|---|---|\n| $$\\lim_{x\\to 1}\\frac{x^2-x}{x^2+x-2}$$ | $$\\lim_{x\\to 2}\\frac{x-2}{\\sqrt{x}-\\sqrt{2}}$$ |\n| $$\\lim_{x\\to 1}\\frac{2-\\sqrt{a-x}}{1-x}=b\\;\\text{収束する}$$ | $$\\lim_{x\\to -\\infty}x(\\sqrt{x^2-2x+3}+x-a)\\;\\text{収束する}$$ |\n\n:::\n\n<details><summary>解答</summary>\n\n|||\n|---|---|\n|$$\\frac{1}{3}$$|$$2\\sqrt{2}$$|\n|$$a=5,\\;b=-\\frac{1}{4}$$|$$a=1,\\;b=-1$$|\n\n</details>\n\n::: {.callout-tip icon=false}\n\n## 問題\n\n$$f(x)=\\frac{2ax^2-(a-2)x-1}{ax^2-(a^2-1)x-a}$$\nと定義された関数があり，次の式が成り立つように $a$ の値を定めよ．\n$$\\lim_{x \\to 1}f(x)=\\frac{1}{2}$$\n\n:::\n\n<details><summary>解答</summary>\n\n$$f(x)=\\frac{(2x-1)(ax+1)}{(x-a)(ax+1)}=\\frac{2x-1}{x-a}$$\nとなっているので，極限を計算すると\n$$\\frac{1}{1-a}=\\frac{1}{2}$$\n$$a=-1$$\n\nとわかる．\n\n</details>\n\n## 商微分\n\nある関数 $f(x)$ を考えてみることにしましょう．この関数の振る舞いを考える際には定義式自体の形を見て，対称性や式変形などを駆使することが多いと思われます．ここではその振る舞いを考える方法の一つを紹介してみたいと思います．\n\n![](images/intro-1.png)\n\n上の図のように， $f(x)$ が $x=a$ から $x=b=a+\\Delta x$ だけ変化して場合に， $\\Delta y$ だけの変化が起きるものとします．$\\Delta x,\\; \\Delta y$ は一つの変数であり，増分と呼ばれます．\n\nその時次の式が成り立つかと思われます．\n\n$$\\Delta y = \\frac{f(b)-f(a)}{b-a} \\Delta x$$\n\nこの式を次のように変形することによって，この式の概要が見やすくなるでしょう．\n\n$$ f(b) = f(a) + \\frac{\\Delta y}{\\Delta x}(b-a) $$\n\nこの式が表すものとは， $f(b)$ の値が $f(a)$ の値から $\\frac{\\Delta y}{\\Delta x}(b-a)=\\text{ABの傾き}\\times a\\text{と}b\\text{の違いの分}$ だけずれているということになるわけです．\n\nこの時， $\\frac{\\Delta y}{\\Delta x}$ の値を $\\Delta x\\to 0$ と極限をとって考えれば，ABの傾きは点Aにおける接線の傾きになるわけです．このとき，次のように書き記すことにします．\n\n$$\\lim_{\\Delta x \\to 0}\\frac{\\Delta y}{\\Delta x}=\\dv{y}{x}=y'=f'(x)$$\n\nこの値のことを微分係数と呼んでいます．先ほどの式を微分係数を使って書き直してあげれば次のようになるわけです．\n\n$$ f(b) = f(a) + \\frac{\\Delta y}{\\Delta x}(b-a) $$\n\n$$ \\Delta y = \\dv{y}{x} \\Delta x$$\n\nここで近似値にしたのは， $\\Delta x$ をしっかりと極限とっていないからですが，今までやってきたことが接線を使って近似をしているというのがわかりやすい形なので採用しました．\n\nこの式の言わんとするところは，十分小さな $\\Delta x$ に関して言えば $\\Delta y$ は接戦の傾きで近似できるということです．\n\n以上のことを実際の具体的な関数でやってみましょう．例えば， $f(x)=x^2$ などを考えれば\n\n$$\\Delta y = \\frac{b^2-a^2}{b-a} \\Delta x = (b+a) \\Delta x = (2a+\\Delta x) \\Delta x$$\n\nと式変形がなされるわけです．これによって $\\Delta y,\\; \\Delta x$ の比は次のように書き表され\n\n$$\\frac{\\Delta y}{\\Delta x} = 2a + \\Delta x$$\n\nとなります．そして，極限を取ることによって\n\n$$\\dv{y}{x}=2a$$\n\nとなります．このことを $f(x)$ の $x=a$ における微分係数は $2a$ であると呼び，次のように表すことが多いです．\n\n$$ \\dv{y}{x}|_{x=a}=f'(a)=2a$$\n\nまた， $a$ という具体的に代入した値ではなく，任意の $x$ についても同様なことが言えるため，\n\n$$ \\dv{y}{x}=f'(x)=2x$$\n\nと書くことになります．この時， $f(x)$ の導関数は $f'(x)=2x$ などと呼びます．以上の議論を最初から $\\Delta x,\\: \\Delta y$ が微小分，つまり， $\\dd x,\\: \\dd y$ としてすることもでき，その場合は\n\n$$\\dd y = \\frac{b^2-a^2}{b-a} \\dd x = (b+a) \\dd x = (2a+\\dd x) \\dd x = 2a \\dd x + (\\dd x)^2= 2a \\dd x$$\n\n$$\\dv{y}{x} = 2a$$\n\nここで注目して欲しいのは， $\\dd y$ を表す式の中で， $\\dd x$ の一次以上の項が消えていることです．これは極限を取ると消えてしまうからですね．\n\n以上述べたように，微分を考える理由とは，接線で曲線を近似してみようという試みであり，また，曲線を非常に小さな部分で見てあげれば直線になると考えていることになります．\n\n実際に問題を解いてみましょう．\n\n::: {.callout-warning icon=false}\n\n## 例題\n\n次の関数の導関数を求めよ．\n$$f(x)=x^3+x+1$$\n\n:::\n\n<details><summary>解答</summary>\n\n $a=x,\\;b=a+\\Delta x$ とする．\n$$\\Delta y = \\frac{f(b)-f(a)}{b-a}\\Delta x$$\n$$\\frac{f(b)-f(a)}{b-a}=\\frac{f(a+\\Delta x)-f(a)}{a+\\Delta x -a} $$\n$$= \\frac{3x^2\\Delta x + 3x\\Delta x^2 + \\Delta x ^3 + \\Delta x}{\\Delta x}$$\n$$=3x^2+ 3x\\Delta x + \\Delta x ^2 + 1 \\to_{\\Delta x \\to 0} 3x^2+1$$\n$$\\dv{y}{x}=3x^2+1$$\n\n</details>\n\nここで注目して欲しいのは， $\\Delta y$ を表す式の中で， $\\Delta x$ の2次以上の項が消えていることです．導関数を求める極限の計算では完全に消滅しますが， $\\Delta x$ が $0$ に比較的に近いだけの値を考えている時の近似計算でも同様に無視したりします．このことを一次近似と呼んでいます．具体的な問題は後半にあるので，手を動かしてやってみましょう．\n\n次に導関数に慣れてもらうために問題を置いておきます．\n\n::: {.callout-tip icon=false}\n\n## 問題\n\n次の関数の導関数を求めよ．\n\n|||\n|---|---|\n| $$x^2$$ | $$\\sqrt{x}$$ |\n| $$(x+1)(x+2)$$ | $$\\frac{1}{x}$$ |\n| $$x\\sqrt{x}$$ | $$x^6+x^5+x^4$$ |\n\n:::\n\n<details><summary>解答</summary>\n\n|||\n|---|---|\n| $$2x$$ | $$\\frac{\\sqrt{x+\\Delta x}-\\sqrt{x}}{\\sqrt{x}}=\\frac{\\Delta x}{\\Delta x (\\sqrt{x+\\Delta x}+\\sqrt{x})}$$ $$\\frac{1}{2\\sqrt{x}}$$ |\n| $$2x+3$$ | $$-\\frac{1}{x^2}$$ |\n| $$\\frac{3}{2}\\sqrt{x}$$ | $$6x^5+5x^4+4x^3$$ |\n\n</details>\n\n::: {.callout-tip icon=false}\n\n## 問題\n\n次の極限値を $f,f'$ を用いて表せ．\n\n$$\\lim_{x\\to a}\\frac{x^nf(x)-a^nf(a)}{x^n-a^n}$$\n\n:::\n\n<details><summary>解答</summary>\n\n$$f(a)+\\frac{a}{n}f'(a)$$\n\n</details>\n\n::: {.callout-tip icon=false}\n\n## 問題\n\n次の値を近似して解け．\n\n$$1024^2,\\; \\sqrt{74}$$\n\n:::\n\n<details><summary>解答</summary>\n\n$f(x)=x^2$ とする．\n$$f(x+a) \\approx f(x) + f'(x) \\times a$$\nなので， $x=1000,\\; a=24$ を代入することによって \n$$1000^2 + 1000 \\times 24 \\approx 10024000$$\n\nと近似できる．\n\n後半の問題も同じく， $f(x)=\\sqrt{x},\\; x=64,\\; a=10$ とおいて解けば，\n$$\\sqrt{64+10} \\approx \\sqrt{64} + \\frac{1}{2\\sqrt{64}} \\times 10 \\approx 8.6 $$\n\n</details>\n\n\n::: {.callout-tip icon=false}\n\n## 問題\n\n次の事実を証明せよ．\n\n$$(f+g)'=f'+g'$$\n\n$$ (fg)' = f'g+fg'$$\n\n$$\\dv{x}\\frac{1}{g}=-\\frac{g'(x)}{\\{g(x)\\}^2}$$\n\n$$\\left\\{ \\frac{f}{g} \\right\\} ' = \\frac{f'g-fg'}{g^2}$$\n\n$$\\dv{x} x^n = nx^{n-1}$$\n\n:::\n\n<details><summary>解答</summary>\n\n$(f+g)'=f'+g'$ は自力でせよ．\n\n$ (fg)' = f'g+fg'$ は厳密な証明ではなく，一次近似を駆使して説明する．厳密な証明は自ら調べよ．\n\n$$f(x+\\Delta x)g(x+\\Delta x) \\approx (f(x)+f'(x)\\Delta x)(g(x)+g'(x)\\Delta x)$$\n\nここで二次以上の変化量( $\\Delta$ 付きの値)は無視されるので，\n$$f(x+\\Delta x)g(x+\\Delta x) \\approx f(x)g(x) + f'(x)g(x)\\Delta x + f(x)g'(x)\\Delta x$$\n$$\\frac{f(x+\\Delta x)g(x+\\Delta x)-f(x)g(x)}{\\Delta x} = f'(x)g(x)+f(x)g'(x)$$\n\n後半の問題は有名問題であり，今までの知識を使って自力で解決せよ．\n\n最後の問題については二項定理を用いて自ら解決せよ．なおこの定理は $n$ が整数の時だけでなく，実数のときにも成り立つが，その証明は難しいのでここでは省略する．ただし，これからは使っていくので，知っておくこと．\n</details>\n\nここで，このテキストの特徴として，詳しい解答を書いていないことが多々あることでしょう．これは，特定の問題までの内容を理解した人ならば違和感なく解ける問題や，有名すぎるあまりにわざわざ書くこともないだろうと思われる問題について当てはまることになります．ただし，ぜひともこの考え方を習得してもらいたいと思われる際には，詳しい解答を書くように心がけています．\n\nまた，この本では，読者が実際に手を動かして問題を解くことを前提にして書いており，問題と解答を読むだけではなかなか問題解決能力が身につかないのではないかと思われます．ご注意ください．\n\n## 合成関数の微分法\n\n次に次の問題を考えてみましょう．\n\n::: {.callout-tip icon=false}\n\n## 問題\n\n次の事実を証明せよ．\n\n$$y=x^2+x,\\; z=y^3+1$$\nとしたとき，次の値をそれぞれ求めよ．\n$$\\dv{y}{x},\\;\\dv{z}{y},\\;\\dv{z}{x}$$\n\n:::\n$$\\dv{y}{x}=2x+1,\\; \\dv{z}{y}=3y^2$$\nこれら二つは簡単でしょう．では， $\\dv{z}{x}$ はどうしたらいいでしょうか．分数と同様にするべきでしょうか．はい，その通りです．\n\n$$\\dv{z}{x}=3y^2(2x+1)=3(2x+1)(x^2+x)^2$$\n\n::: {.callout-note icon=false}\n\n## 定理\n\n$$\\dv{y}{x}\\cdot \\dv{z}{y}=\\dv{z}{x}$$\n\n:::\n\n証明は\n\n$$\\lim_{\\Delta x \\to 0}\\frac{\\Delta z}{\\Delta x}=\\lim_{\\Delta x \\to 0}\\frac{\\Delta z}{\\Delta y}\\frac{\\Delta y}{\\Delta x}$$\n\nによって大まかに達成されます．ただし， $\\Delta y \\neq 0$\nであることを前提にしている証明なので，厳密には証明になっていませんが，厳密な証明は難しいので省略させていただきます．\n\nそして，この問題のおかげで私たちは次の問題を解決したことになるのです．\n\n$z=(x^2+x)^3+1$ の導関数を求めよ．\n\nこれを合成関数の微分法と呼ばれるもので，賢そうな人たちがチェーンルールと呼んでいるものです．\n\nでは，この定理を使って問題を解いていきましょう．\n\n::: {.callout-warning icon=false}\n\n## 例題\n\n次の関数の導関数を求めよ．\n$$f(x)=\\sqrt[3]{\\frac{x^2}{1-x}}$$\n\n:::\n\n<details><summary>解答</summary>\n\n$y=f(x),\\; u=\\frac{x^2}{1-x}$ とする．この時 $y=\\sqrt[3]{u}$ となるため\n\n$$\\dv{y}{x}=\\dv{y}{u}\\dv{u}{x}=\\frac{1}{3u^{2/3}}\\frac{2x-x^2}{(1-x)^2}=\\frac{1}{3}\\left(\\frac{1-x}{x^2}\\right)^{2/3}\\frac{2x-x^2}{(1-x)^2}$$\n\n</details>\n\n::: {.callout-tip icon=false}\n\n## 問題\n\n次の関数の導関数を求めよ．\n\n|||\n|---|---|\n| $$\\sqrt{a^2-x^2}$$ | $$x+\\sqrt{x^2-1}$$ |\n| $$\\frac{x}{\\sqrt{x^2+1}}$$ | $$\\frac{\\sqrt{a^2+x^2}-\\sqrt{a^2-x^2}}{\\sqrt{a^2+x^2}+\\sqrt{a^2-x^2}}$$ |\n\n$x=y\\sqrt{y+1}$ の時， $\\dv{y}{x}$ を求めよ．\n\n:::\n\n<details><summary>解答</summary>\n\n|||\n|---|---|\n| $$-\\frac{x}{\\sqrt{a^2-x^2}}$$ | $$1+\\frac{x}{\\sqrt{x^2-1}}$$ |\n| $$\\frac{1}{(x^2+1)\\sqrt{x^2+1}}$$ | $$\\frac{2a^2(a^2-\\sqrt{a^4-x^4})}{x^3\\sqrt{a^4-x^4}}$$ |\n\n次の問題については，\n\n$$\\dv{x}{y}=\\frac{3y+2}{2\\sqrt{y+1}}$$\n$$\\dv{y}{x}=\\frac{2\\sqrt{y+1}}{3y+2}$$\n\nこれは逆関数の微分法と呼ばれるものだが，\n\n$$\\lim_{\\Delta x \\to 0}\\frac{\\Delta y}{\\Delta x}=\\lim_{\\Delta x \\to 0}\\frac{1}{\\frac{\\Delta y}{\\Delta x}}$$\n\nを考えれば明らかである．ただしこの証明は連続性などの過程を飛ばした直感的なものに過ぎず，厳密な証明はここではしない．\n\n</details>\n\n## 増減\n\nまず，定理から述べようと思います．\n\n::: {.callout-note icon=false}\n\n## 定理\n\nとある区間において，\n\n - $f'(x) \\geq 0$ であれば，この区間では $f(x)$ は増加する．\n - $f'(x) \\leq 0$ であれば，この区間では $f(x)$ は減少する．\n\n:::\n\nこの定理については，ある区間の内で接戦の傾きが常に正ならば，関数は増加し続ける，また逆も然りということを述べているわけです．この定理がどのように使われるかは，次の問題で話すことにしましょう．\n\n::: {.callout-warning icon=false}\n\n## 例題\n\n次の関数のグラフの概形を描け．\n$$f(x)=x^3-3x+1$$\n\n:::\n\n<details><summary>解答</summary>\n\n$$f'(x)=3(x+1)(x-1)$$\n\n導関数の形から，次のことが言える．\n\n！[](images/intro-2.png)\n\nこの表のことは増減表と呼ばれる．初学のうちは書いておくと混乱が少ないが，慣れてきたのならばわざわざ書かなくとも良い．\n\n上の増減表によってグラフの概形は次のようになる．\n\n![](images/intro-3.png)\n\nまた， $x=-1,\\; x=1$ の場所は増減が変化する点であり，この点のことを極大点，極小点などと呼んでいる．\n\n</details>\n\n\n## 面積と区分求積法\n\n小学校以来，何となく扱ってきた「面積」というものについて，少し詳しく述べていきます．\n\nまず，長方形の面積は「縦$\\times$横」と決めましょう．このことについては特に異論はないと思います．この長方形の面積を手がかりに，いろいろな図形の面積，特にグラフと軸で囲われた部分の面積を考えていくことにしましょう．\n\n $xy$ 平面上で， $y=f(x)$ のグラフと，直線$x=a,x=b$で囲まれる領域の面積$S$を考えます．ここでは $f(x)$ は区間 $[a,b]$ で連続な関数であるとします．\n\n（図）\n\nこのように，区間 $[a,b]$ を $n$ 分割し，区間 $\\left[a+\\displaystyle\\frac{k-1}{n}(b-a),a+\\displaystyle\\frac{k}{n}(b-a)\\right]$ における $f(x)$の最大値を$M_k$ ，最小値を $m_k$ とします．このとき， $\\displaystyle\\sum_{k=1}^{n}\\displaystyle\\frac{M_k}{n}$ は $S$ より少し大きく， $\\displaystyle\\sum_{k=1}^{n}\\displaystyle\\frac{m_k}{n}$ は $S$ より少し小さいことが下の図から分かると思います．\n\n（図）\n\nそして，この分割をどんどん細かくしたとき，すなわち$n\\to\\infty$のとき，$\\displaystyle\\sum_{k=1}^{n}\\displaystyle\\frac{M_k}{n}$および，$\\displaystyle\\sum_{k=1}^{n}\\displaystyle\\frac{m_k}{n}$ は $S$ に限りなく近づくと考えられます．\n\n上では各区間における $f(x)$ の最大値，最小値をとって考えましたが，実は区間 $\\left[a+\\displaystyle\\frac{k-1}{n}(b-a),a+\\displaystyle\\frac{k}{n}(b-a)\\right]$ ごとに好きな代表点 $x_k$ をとって， $M_k,m_k$ の代わりに $f(x_k)$ を考えても問題ありません．以上を踏まえて，\n$$\\displaystyle\\lim_{n\\to\\infty} \\displaystyle\\sum_{k=1}^{n}\\displaystyle\\frac{b-a}{n}f(x_k)$$\nを， $y=f(x)$ のグラフと，直線$x=a,x=b$で囲まれる領域の面積 $S$ であると定めることにします．この考え方は，は区分求積法と呼ばれています．\n\n::: {.callout-note icon=false}\n\n## 定義\n\n$y=f(x)$ のグラフと，直線$x=a,x=b$で囲まれる領域の面積 $S$を \n$$\\displaystyle\\lim_{n\\to\\infty} \\displaystyle\\sum_{k=1}^{n}\\displaystyle\\frac{b-a}{n}f(x_k)$$\nで定め，これを\n$$\\displaystyle\\int_{a}^{b}f(x)dx$$\nとかく．\n:::\n\n\n<details><summary>補足</summary>\n\nここで述べた面積（ついては積分）の定義は，正確なものではありませんが，少なくとも連続関数についてはこの定義で問題を生じないので，このまま進めることにします．\n\n</details>\n\n::: {.callout-tip icon=\"false\"}\n\n## 問題\n\n次の値を求めよ．ただし，代表点$x_k$は$\\displaystyle\\frac{k}{n}$とせよ．\n\n$$\\displaystyle\\int_{0}^{1} x^2dx$$\n\n:::\n<details><summary>解答</summary>\n\n\\begin{align*}\n\\displaystyle\\int_{0}^{1} x^2dx　&= \\displaystyle\\lim_{n\\to\\infty} \\displaystyle\\sum_{k=1}^{n}\\displaystyle\\frac{1}{n}\\cdot \\left(\\displaystyle\\frac{k}{n}\\right)^2\\\\\n&=\\displaystyle\\lim_{n\\to\\infty}\\displaystyle\\frac{1}{n^3}\\displaystyle\\sum_{k=1}^{n}k^2\\\\\n&=\\displaystyle\\lim_{n\\to\\infty}\\displaystyle\\frac{1}{n^3}\\cdot \\displaystyle\\frac{n(n+1)(2n+1)}{6}\\\\\n&=\\displaystyle\\frac{1}{3}\n\\end{align*}\n\n</details>\n"},"formats":{"html":{"execute":{"fig-width":7,"fig-height":5,"fig-format":"retina","fig-dpi":96,"df-print":"default","error":false,"eval":true,"cache":null,"freeze":false,"echo":true,"output":true,"warning":true,"include":true,"keep-md":false,"keep-ipynb":false,"ipynb":null,"enabled":null,"daemon":null,"daemon-restart":false,"debug":false,"ipynb-filters":[],"engine":"markdown"},"render":{"keep-tex":false,"keep-source":false,"keep-hidden":false,"prefer-html":false,"output-divs":true,"output-ext":"html","fig-align":"default","fig-pos":null,"fig-env":null,"code-fold":"none","code-overflow":"scroll","code-link":false,"code-line-numbers":false,"code-tools":false,"tbl-colwidths":"auto","merge-includes":true,"latex-auto-mk":true,"latex-auto-install":true,"latex-clean":true,"latex-max-runs":10,"latex-makeindex":"makeindex","latex-makeindex-opts":[],"latex-tlmgr-opts":[],"latex-input-paths":[],"latex-output-dir":null,"link-external-icon":false,"link-external-newwindow":false,"self-contained-math":false,"format-resources":[]},"pandoc":{"standalone":true,"wrap":"none","default-image-extension":"png","to":"html","output-file":"intro.html"},"language":{},"metadata":{"lang":"en","fig-responsive":true,"quarto-version":"1.2.269","bibliography":["references.bib"],"theme":{"light":"flatly","dark":"darkly"}},"extensions":{"book":{"multiFile":true}}},"pdf":{"execute":{"fig-width":5.5,"fig-height":3.5,"fig-format":"pdf","fig-dpi":300,"df-print":"default","error":false,"eval":true,"cache":null,"freeze":false,"echo":true,"output":true,"warning":true,"include":true,"keep-md":false,"keep-ipynb":false,"ipynb":null,"enabled":null,"daemon":null,"daemon-restart":false,"debug":false,"ipynb-filters":[],"engine":"markdown"},"render":{"keep-tex":false,"keep-source":false,"keep-hidden":false,"prefer-html":false,"output-divs":true,"output-ext":"pdf","fig-align":"default","fig-pos":null,"fig-env":null,"code-fold":"none","code-overflow":"scroll","code-link":false,"code-line-numbers":false,"code-tools":false,"tbl-colwidths":true,"merge-includes":true,"latex-auto-mk":true,"latex-auto-install":true,"latex-clean":true,"latex-max-runs":10,"latex-makeindex":"makeindex","latex-makeindex-opts":[],"latex-tlmgr-opts":[],"latex-input-paths":[],"latex-output-dir":null,"link-external-icon":false,"link-external-newwindow":false,"self-contained-math":false,"format-resources":[]},"pandoc":{"pdf-engine":"xelatex","standalone":true,"variables":{"graphics":true,"tables":true},"default-image-extension":"pdf","to":"pdf","output-file":"intro.pdf"},"language":{},"metadata":{"block-headings":true,"bibliography":["references.bib"],"documentclass":"scrreprt"},"extensions":{"book":{}}}}}